setup.py
dag/__init__.py
py_dag.egg-info/PKG-INFO
py_dag.egg-info/SOURCES.txt
py_dag.egg-info/dependency_links.txt
py_dag.egg-info/not-zip-safe
py_dag.egg-info/top_level.txt