Metadata-Version: 1.0
Name: py-dag
Version: 2.4.0
Summary: Directed acyclic graph implementation
Home-page: https://github.com/thieman/py-dag
Author: Travis Thieman
Author-email: travis.thieman@gmail.com
License: MIT
Platform: UNKNOWN
